lib_py/__init__.py
lib_py/demo_class.py
lib_py/demo_function.py
lib_py_itild-0.1.0.dist-info/METADATA
lib_py_itild-0.1.0.dist-info/WHEEL
lib_py_itild-0.1.0.dist-info/top_level.txt
lib_py_itild-0.1.0.dist-info/RECORD
