Metadata-Version: 2.4
Name: lib-py-itild
Version: 0.1.0
Summary: A demo Python package with a function and a class
Author-email: Your Name <your.email@example.com>
Keywords: demo,example,package
Classifier: Development Status :: 3 - Alpha
Classifier: Intended Audience :: Developers
Classifier: License :: OSI Approved :: MIT License
Classifier: Programming Language :: Python :: 3
Classifier: Programming Language :: Python :: 3.13
Requires-Python: >=3.13
